azext_subscription/__init__.py
azext_subscription/_client_factory.py
azext_subscription/_exception_handler.py
azext_subscription/_help.py
azext_subscription/_params.py
azext_subscription/commands.py
azext_subscription/custom.py
azext_subscription/subscription/__init__.py
azext_subscription/subscription/subscription_client.py
azext_subscription/subscription/version.py
azext_subscription/subscription/models/__init__.py
azext_subscription/subscription/models/error_response.py
azext_subscription/subscription/models/location.py
azext_subscription/subscription/models/location_paged.py
azext_subscription/subscription/models/operation.py
azext_subscription/subscription/models/operation_display.py
azext_subscription/subscription/models/operation_paged.py
azext_subscription/subscription/models/subscription.py
azext_subscription/subscription/models/subscription_client_enums.py
azext_subscription/subscription/models/subscription_definition.py
azext_subscription/subscription/models/subscription_definition_paged.py
azext_subscription/subscription/models/subscription_paged.py
azext_subscription/subscription/models/subscription_policies.py
azext_subscription/subscription/models/tenant_id_description.py
azext_subscription/subscription/models/tenant_id_description_paged.py
azext_subscription/subscription/operations/__init__.py
azext_subscription/subscription/operations/subscription_definitions_operation_metadata_operations.py
azext_subscription/subscription/operations/subscription_definitions_operations.py
azext_subscription/subscription/operations/subscriptions_operations.py
azext_subscription/subscription/operations/tenants_operations.py
azext_subscription/tests/__init__.py
azext_subscription/tests/test_subscription_definition_commands.py
subscription-0.1.0.dist-info/DESCRIPTION.rst
subscription-0.1.0.dist-info/METADATA
subscription-0.1.0.dist-info/RECORD
subscription-0.1.0.dist-info/WHEEL
subscription-0.1.0.dist-info/metadata.json
subscription-0.1.0.dist-info/top_level.txt
