Metadata-Version: 2.0
Name: subscription
Version: 0.1.0
Summary: An Azure CLI Extension to manage Subscription Definitions
Home-page: https://github.com/Azure/azure-cli-extensions
Author: Wilco Bauwer
Author-email: wilcob@microsoft.com
License: MIT
Platform: UNKNOWN
Classifier: Development Status :: 4 - Beta
Classifier: Intended Audience :: Developers
Classifier: Intended Audience :: System Administrators
Classifier: Programming Language :: Python
Classifier: Programming Language :: Python :: 2
Classifier: Programming Language :: Python :: 2.7
Classifier: Programming Language :: Python :: 3
Classifier: Programming Language :: Python :: 3.4
Classifier: Programming Language :: Python :: 3.5
Classifier: Programming Language :: Python :: 3.6
Classifier: License :: OSI Approved :: MIT License
